exiftimestamper.py
setup.py
exiftimestamper.egg-info/PKG-INFO
exiftimestamper.egg-info/SOURCES.txt
exiftimestamper.egg-info/dependency_links.txt
exiftimestamper.egg-info/entry_points.txt
exiftimestamper.egg-info/requires.txt
exiftimestamper.egg-info/top_level.txt