Metadata-Version: 1.0
Name: exiftimestamper
Version: 2016.11.27
Summary: A command-line tool to update jpeg file timestamps
Home-page: https://github.com/erjoalgo/exiftimestamper
Author: Ernesto Alfonso
Author-email: erjoalgo@gmail.com
License: LGPL
Platform: UNKNOWN
